connectlm/__init__.py
connectlm/common.py
connectlm/error.py
connectlm/query_chat.py
connectlm/services/__init__.py
connectlm/services/openai_adaptor.py
connectlm/services/tgi_adaptor.py
ConnectLM-0.0.1.dist-info/METADATA
ConnectLM-0.0.1.dist-info/WHEEL
ConnectLM-0.0.1.dist-info/top_level.txt
ConnectLM-0.0.1.dist-info/RECORD
