Metadata-Version: 2.1
Name: ConnectLM
Version: 0.0.1
Summary: Language Model Proxy
Home-page: https://github.com/saaiie/ConnectLM
Author: jaypark
Author-email: jaypark@gmail.com
Keywords: chatbot,ai,ml,llm
Classifier: Programming Language :: Python :: 3.10
Requires-Python: >=3.10
